MANIFEST.in
README.txt
medialog.subskinsiii-configure.zcml
setup.py
docs/HISTORY.txt
docs/INSTALL.txt
docs/LICENSE.GPL
docs/LICENSE.txt
medialog/.DS_Store
medialog/__init__.py
medialog.subskinsiii.egg-info/PKG-INFO
medialog.subskinsiii.egg-info/SOURCES.txt
medialog.subskinsiii.egg-info/dependency_links.txt
medialog.subskinsiii.egg-info/entry_points.txt
medialog.subskinsiii.egg-info/namespace_packages.txt
medialog.subskinsiii.egg-info/not-zip-safe
medialog.subskinsiii.egg-info/requires.txt
medialog.subskinsiii.egg-info/top_level.txt
medialog/subskinsiii/.DS_Store
medialog/subskinsiii/__init__.py
medialog/subskinsiii/configure.zcml
medialog/subskinsiii/exportimport.py
medialog/subskinsiii/profiles.zcml
medialog/subskinsiii/setuphandlers.py
medialog/subskinsiii/skins.zcml
medialog/subskinsiii/tests.py
medialog/subskinsiii/version.txt
medialog/subskinsiii/browser/.DS_Store
medialog/subskinsiii/browser/__init__.py
medialog/subskinsiii/browser/configure.zcml
medialog/subskinsiii/browser/interfaces.py
medialog/subskinsiii/browser/subskinsloader.pt
medialog/subskinsiii/browser/viewlet.pt
medialog/subskinsiii/browser/viewlets.py
medialog/subskinsiii/browser/images/README.txt
medialog/subskinsiii/browser/stylesheets/README.txt
medialog/subskinsiii/browser/stylesheets/main.css
medialog/subskinsiii/profiles/.DS_Store
medialog/subskinsiii/profiles/default/.DS_Store
medialog/subskinsiii/profiles/default/cssregistry.xml
medialog/subskinsiii/profiles/default/import_steps.xml
medialog/subskinsiii/profiles/default/jsregistry.xml
medialog/subskinsiii/profiles/default/medialog.subskinsiii_various.txt
medialog/subskinsiii/profiles/default/metadata.xml
medialog/subskinsiii/profiles/default/skins.xml
medialog/subskinsiii/profiles/default/subskins_choices.xml
medialog/subskinsiii/profiles/default/viewlets.xml
medialog/subskinsiii/profiles/viewletsorder01/.DS_Store
medialog/subskinsiii/profiles/viewletsorder01/cssregistry.xml
medialog/subskinsiii/profiles/viewletsorder01/import_steps.xml
medialog/subskinsiii/profiles/viewletsorder01/jsregistry.xml
medialog/subskinsiii/profiles/viewletsorder01/medialog.subskinsiii_various.txt
medialog/subskinsiii/profiles/viewletsorder01/metadata.xml
medialog/subskinsiii/profiles/viewletsorder01/skins.xml
medialog/subskinsiii/profiles/viewletsorder01/types.xml
